gpsa/__init__.py
gpsa/models/__init__.py
gpsa/models/gpsa.py
gpsa/models/vgpsa.py
gpsa/plotting/__init__.py
gpsa/plotting/callbacks.py
gpsa/util/__init__.py
gpsa/util/util.py
gpsa_engelhardt-0.6.15.dist-info/licenses/LICENSE.txt
gpsa_engelhardt-0.6.15.dist-info/METADATA
gpsa_engelhardt-0.6.15.dist-info/WHEEL
gpsa_engelhardt-0.6.15.dist-info/top_level.txt
gpsa_engelhardt-0.6.15.dist-info/RECORD
