Metadata-Version: 2.4
Name: gpsa-engelhardt
Version: 0.6.15
Summary: Gaussian Process Spatial Alignment (GPSA)
Home-page: https://github.com/engelhardtgpsa/spatial-alignment
Author: Andy Jones and Barbara Engelhardt
Author-email: engelhardtgpsa@gmail.com
License: Apache-2.0
Classifier: Development Status :: 4 - Beta
Classifier: Intended Audience :: Science/Research
Classifier: Programming Language :: Python :: 3
Classifier: Programming Language :: Python :: 3.10
Classifier: Programming Language :: Python :: 3.11
Classifier: Operating System :: OS Independent
Classifier: Topic :: Scientific/Engineering :: Artificial Intelligence
Classifier: License :: OSI Approved :: Apache Software License
Requires-Python: >=3.10, <3.12
License-File: LICENSE.txt
Requires-Dist: torch==2.2.2
Requires-Dist: numpy==1.26.4
Requires-Dist: pandas==2.2.2
Requires-Dist: scikit-learn==1.3.2
Requires-Dist: pcpca==0.3
Requires-Dist: plottify==1.1
Requires-Dist: scanpy==1.9.1
Requires-Dist: scipy==1.12.0
Requires-Dist: seaborn>=0.13.2
Requires-Dist: statsmodels==0.14.0
Requires-Dist: anndata==0.8.0
Requires-Dist: auto_mix_prep==0.2.0
Requires-Dist: matplotlib>=3.8.0
Requires-Dist: tqdm==4.64.0
Requires-Dist: squidpy==1.1.2
Provides-Extra: dev
Requires-Dist: flake8; extra == "dev"
Requires-Dist: pytest; extra == "dev"
Requires-Dist: pip-tools; extra == "dev"
Provides-Extra: docs
Requires-Dist: pdoc; extra == "docs"
Requires-Dist: py-cpuinfo; extra == "docs"
Requires-Dist: Cython; extra == "docs"
Requires-Dist: numpy; extra == "docs"
Dynamic: author
Dynamic: author-email
Dynamic: classifier
Dynamic: description
Dynamic: description-content-type
Dynamic: home-page
Dynamic: license
Dynamic: license-file
Dynamic: provides-extra
Dynamic: requires-dist
Dynamic: requires-python
Dynamic: summary
